semantic_regex/__init__.py
semantic_regex/neuronpedia.py
semantic_regex/prompts/semantic_regex_prompt.py
semantic_regex/semantic_regex.py
semantic_regex/util.py
semantic_regex-0.1.0.dist-info/WHEEL
semantic_regex-0.1.0.dist-info/METADATA
semantic_regex-0.1.0.dist-info/RECORD
