Metadata-Version: 2.3
Name: semantic-regex
Version: 0.1.0
Summary: Auto-interpreting LLM features with a structured language
Keywords: interpretability,autointerp,semantic regex
Author: Angie Boggust, Donghao Ren, Yannick Assogba, Dominik Moritz, Arvind Satyanarayan, Fred Hohman
Author-email: Angie Boggust <aboggust@csail.mit.edu>, Donghao Ren <donghao@apple.com>, Yannick Assogba <yassogba@apple.com>, Dominik Moritz <domoritz@apple.com>, Arvind Satyanarayan <arvindsatya@mit.edu>, Fred Hohman <fredhohman@apple.com>
License: Copyright (C) 2025 Apple Inc. All Rights Reserved.
Requires-Dist: dspy>=3.0.0
Requires-Dist: numpy>=2.3.0
Requires-Dist: requests>=2.32.0
Requires-Python: >=3.11
Project-URL: homepage, https://apple.github.io/ml-semantic-regex
Project-URL: source, https://github.com/apple/ml-semantic-regex
